mammath/Complex.py
mammath/Fractions.py
mammath/__init__.py
mammath/algebra.py
mammath/base_conversions.py
mammath/calculus.py
mammath/constants.py
mammath/coord_geometry.py
mammath/deleted.py
mammath/deprecated.py
mammath/divisibility_checks.py
mammath/fibonacci.py
mammath/geometry.py
mammath/graphing.py
mammath/helper.py
mammath/linalg.py
mammath/misc.py
mammath/operations.py
mammath/physics.py
mammath/prime_numbers.py
mammath/sequences.py
mammath/shunting_yard.py
mammath/special_numbers.py
mammath/tables.py
mammath/teachers.py
mammath/trig_functions.py
mammath/unit_conversions.py
mammath-0.3.1.dist-info/METADATA
mammath-0.3.1.dist-info/WHEEL
mammath-0.3.1.dist-info/top_level.txt
mammath-0.3.1.dist-info/RECORD
