Metadata-Version: 2.1
Name: mammath
Version: 0.3.1
Summary: A comprehensive package for advanced mathematics and science in Python
Author: Vihaan Mathur & Harihar Rengan
Author-email: vihaan.harihar314@gmail.com
Classifier: Programming Language :: Python :: 3
Classifier: License :: OSI Approved :: MIT License
Classifier: Operating System :: OS Independent
Requires-Python: >=3.6
Requires-Dist: tabulate
Requires-Dist: numpy
Requires-Dist: matplotlib
Requires-Dist: keyboard
